wsjt_all/__init__.py
wsjt_all/load_sessions.py
wsjt_all/plotter_dual.py
wsjt_all/plotter_single.py
wsjt_all/run.py
wsjt_all/utils.py
wsjt_all-1.7.2.dist-info/licenses/LICENSE
wsjt_all-1.7.2.dist-info/METADATA
wsjt_all-1.7.2.dist-info/WHEEL
wsjt_all-1.7.2.dist-info/entry_points.txt
wsjt_all-1.7.2.dist-info/top_level.txt
wsjt_all-1.7.2.dist-info/RECORD
